{
  "project_info": {
    "project_number": "1085838500345",
    "project_id": "letspadel-38070",
    "storage_bucket": "letspadel-38070.appspot.com"
  },
  "client": [
    {
      "client_info": {
        "mobilesdk_app_id": "1:1085838500345:android:0ceb45694fdce06845dd28",
        "android_client_info": {
          "package_name": "com.project.padel"
        }
      },
      "oauth_client": [],
      "api_key": [
        {
          "current_key": "AIzaSyDkFnmiqZmd4Dtzf2dEfHg4vnXsDxmCYUI"
        }
      ],
      "services": {
        "appinvite_service": {
          "other_platform_oauth_client": []
        }
      }
    }
  ],
  "configuration_version": "1"
}